README.rst
setup.cfg
setup.py
seaborn/logger/__init__.py
seaborn/logger/logger.py
seaborn/logger/skip_traceback.py
seaborn_logger.egg-info/PKG-INFO
seaborn_logger.egg-info/SOURCES.txt
seaborn_logger.egg-info/dependency_links.txt
seaborn_logger.egg-info/requires.txt
seaborn_logger.egg-info/top_level.txt
test/test_logger.py
test/test_trace_logger.py