Metadata-Version: 1.1
Name: seaborn-logger
Version: 0.0.4
Summary: SeabornLogger enables the streaming of the data relevant ot a program's to a logging file
Home-page: https://github.com/SeabornGames/Logger
Author: Ben Christenson
Author-email: Python@BenChristenson.com
License: MIT License
Download-URL: https://github.com/SeabornGames/Logger/tarball/download
Keywords: logging
Platform: UNKNOWN
Classifier: Intended Audience :: Developers
Classifier: Natural Language :: English
Classifier: License :: Other/Proprietary License
Classifier: Operating System :: POSIX :: Linux
Classifier: Programming Language :: Python
Classifier: Programming Language :: Python :: 2.7
Classifier: Programming Language :: Python :: 3.6
